dcpAlive/__init__.py
dcpAlive-1.0.2.dist-info/LICENSE
dcpAlive-1.0.2.dist-info/METADATA
dcpAlive-1.0.2.dist-info/WHEEL
dcpAlive-1.0.2.dist-info/top_level.txt
dcpAlive-1.0.2.dist-info/RECORD
