Metadata-Version: 2.1
Name: dcpAlive
Version: 1.0.2
Summary: DCP-o-Matic with Progress Bars
Home-page: https://github.com/thegreentimtam/dcpAlive
Author: Tim Green
Author-email: the.green.timtam@gmail.com
License: MIT
License-File: LICENSE
Requires-Dist: alive-progress
Requires-Dist: ffAlive
